entise/__init__.py
entise/constants/__init__.py
entise/constants/columns.py
entise/constants/constants.py
entise/constants/general.py
entise/constants/objects.py
entise/constants/ts_types.py
entise/constants/units.py
entise/core/__init__.py
entise/core/base.py
entise/core/base_auxiliary.py
entise/core/generator.py
entise/core/registry.py
entise/core/runner.py
entise/core/utils.py
entise/data/dhw/README.md
entise/data/dhw/ashrae/dhw_activity_weekend.csv
entise/data/dhw/hendron_burch/dhw_demand_by_occupants.csv
entise/data/dhw/iea_annex42/dhw_demand_by_household_type.csv
entise/data/dhw/jordan_vajen/dhw_activity.csv
entise/data/dhw/jordan_vajen/dhw_demand_by_dwelling.csv
entise/data/dhw/jordan_vajen/units.txt
entise/data/dhw/probabilistic/README.md
entise/data/dhw/probabilistic/cold_water_temperature.csv
entise/data/dhw/probabilistic/dhw_activity.csv
entise/data/dhw/probabilistic/dhw_activity_weekend.csv
entise/data/dhw/probabilistic/dhw_demand_by_dwelling.csv
entise/data/dhw/probabilistic/dhw_demand_by_household_type.csv
entise/data/dhw/probabilistic/dhw_demand_by_occupants.csv
entise/data/dhw/shared/cold_water_temp_vdi4655.csv
entise/methods/__init__.py
entise/methods/auxiliary/__init__.py
entise/methods/auxiliary/internal/__init__.py
entise/methods/auxiliary/internal/selector.py
entise/methods/auxiliary/internal/strategies.py
entise/methods/auxiliary/solar/__init__.py
entise/methods/auxiliary/solar/selector.py
entise/methods/auxiliary/solar/strategies.py
entise/methods/auxiliary/ventilation/__init__.py
entise/methods/auxiliary/ventilation/selector.py
entise/methods/auxiliary/ventilation/strategies.py
entise/methods/dhw/__init__.py
entise/methods/dhw/defaults.py
entise/methods/dhw/jordan_vajen.py
entise/methods/dhw/jordanvajen/__init__.py
entise/methods/dhw/jordanvajen/activity.py
entise/methods/dhw/jordanvajen/calculation.py
entise/methods/dhw/jordanvajen/temperature.py
entise/methods/dhw/jordanvajen/utils.py
entise/methods/electricity/__init__.py
entise-1.1.0.dist-info/METADATA
entise-1.1.0.dist-info/WHEEL
entise-1.1.0.dist-info/licenses/LICENSE
entise-1.1.0.dist-info/RECORD
