Metadata-Version: 2.4
Name: entise
Version: 1.1.0
Summary: A tool for generating time series data related to energy systems and building operations
Project-URL: Homepage, https://gitlab.lrz.de/tum-ens/need/entise
Project-URL: Bug Tracker, https://gitlab.lrz.de/tum-ens/need/entise/-/issues
Project-URL: Documentation, https://entise.readthedocs.io
Author-email: Markus Doepfert <markus.doepfert@tum.de>
License: MIT
License-File: LICENSE
Keywords: energy,simulation,time series
Classifier: Development Status :: 3 - Alpha
Classifier: Intended Audience :: Science/Research
Classifier: License :: OSI Approved :: MIT License
Classifier: Programming Language :: Python :: 3
Classifier: Programming Language :: Python :: 3.10
Classifier: Programming Language :: Python :: 3.11
Classifier: Programming Language :: Python :: 3.12
Classifier: Programming Language :: Python :: 3.13
Classifier: Topic :: Scientific/Engineering
Requires-Python: <3.14,>=3.10
Requires-Dist: cattrs
Requires-Dist: chardet>=5.0.0
Requires-Dist: holidays>=0.50
Requires-Dist: joblib>=1.0.0
Requires-Dist: matplotlib>=3.1.0
Requires-Dist: numpy>=2.0.0
Requires-Dist: openmeteo-requests
Requires-Dist: pandas>=2.0.0
Requires-Dist: pint
Requires-Dist: pvlib>=0.12.0
Requires-Dist: requests-cache
Requires-Dist: retry-requests
Requires-Dist: tqdm>=4.0.0
Requires-Dist: windpowerlib
Provides-Extra: dev
Requires-Dist: mypy>=1.16.0; extra == 'dev'
Requires-Dist: pre-commit>=4.2.0; extra == 'dev'
Requires-Dist: pytest-cov>=6.0.0; extra == 'dev'
Requires-Dist: pytest-mock>=3.14.0; extra == 'dev'
Requires-Dist: pytest>=8.3.4; extra == 'dev'
Requires-Dist: ruff>=0.11.12; extra == 'dev'
Requires-Dist: tox>=4.0.0; extra == 'dev'
Requires-Dist: uv>=0.7.8; extra == 'dev'
Provides-Extra: docs
Requires-Dist: sphinx; extra == 'docs'
Requires-Dist: sphinx-rtd-theme; extra == 'docs'
